testwknd/__init__.py
testwknd/pdf2image.py
testwknd/pdf2text.py
testwknd_unique-1.0.1.dist-info/LICENSE
testwknd_unique-1.0.1.dist-info/METADATA
testwknd_unique-1.0.1.dist-info/WHEEL
testwknd_unique-1.0.1.dist-info/top_level.txt
testwknd_unique-1.0.1.dist-info/RECORD
